secretly/__init__.py
secretly/_impl.py
secretly/test/test_impl.py
secretly-0.2.dist-info/LICENSE
secretly-0.2.dist-info/WHEEL
secretly-0.2.dist-info/METADATA
secretly-0.2.dist-info/RECORD
