Metadata-Version: 1.2
Name: secretly
Version: 0.2
Summary: Perform an asynchronous task with a secret.
Home-page: https://github.com/glyph/secretly
License: UNKNOWN
Author: Glyph
Author-email: glyph@twistedmatrix.com
Classifier: License :: OSI Approved :: MIT License
Requires-Dist: attrs
Requires-Dist: twisted
Requires-Dist: keyring
Requires-Dist: dbus-python; 'linux' in sys_platform
